kube_debug_pod/__init__.py
kube_debug_pod/__main__.py
kube_debug_pod-0.0.7.dist-info/LICENSE
kube_debug_pod-0.0.7.dist-info/METADATA
kube_debug_pod-0.0.7.dist-info/WHEEL
kube_debug_pod-0.0.7.dist-info/entry_points.txt
kube_debug_pod-0.0.7.dist-info/top_level.txt
kube_debug_pod-0.0.7.dist-info/zip-safe
kube_debug_pod-0.0.7.dist-info/RECORD
