Metadata-Version: 2.1
Name: kube-debug-pod
Version: 0.0.7
Summary: CLI to easily create k8s debug pod.
Home-page: https://github.com/skymoore/kube-debug-pod
Author: Sky Moore
Author-email: i@msky.me
License: MIT
Keywords: k8s,debug,kubernetes,debugging,pod
Classifier: Intended Audience :: Developers
Classifier: Natural Language :: English
Classifier: Programming Language :: Python :: 3.9
Classifier: Programming Language :: Python :: 3.10
Classifier: Programming Language :: Python :: 3.11
License-File: LICENSE
Requires-Dist: click (==8.1.3)
Requires-Dist: cloup (==2.0.0)
